[{"0":"87","eventId":"87","1":"1","memberId":"1","2":"Neo4j","title":"Neo4j","3":"2014-03-28","dat":"2014-03-28","4":"11:00","fromTime":"11:00","5":"12:00","till":"12:00","6":"SJT","location":"SJT","7":"   Neo4j Graph Database   ","description":"   Neo4j Graph Database   ","8":"1Neo4j42760.jpg","poster":"1Neo4j42760.jpg","9":"1Neo4j61978.jpg","permission":"1Neo4j61978.jpg","10":"yes","verificationStatus":"yes"},{"0":"90","eventId":"90","1":"1","memberId":"1","2":"NewEvent","title":"NewEvent","3":"2014-03-28","dat":"2014-03-28","4":"11:00","fromTime":"11:00","5":"12:00","till":"12:00","6":"al;dskfj","location":"al;dskfj","7":"asldfkjasldkfjasl;fdj","description":"asldfkjasldkfjasl;fdj","8":"1NewEvent95346.jpg","poster":"1NewEvent95346.jpg","9":"1NewEvent66347.jpg","permission":"1NewEvent66347.jpg","10":"yes","verificationStatus":"yes"},{"0":"89","eventId":"89","1":"1","memberId":"1","2":"Riddler","title":"Riddler","3":"2014-03-26","dat":"2014-03-26","4":"11:00","fromTime":"11:00","5":"12:00","till":"12:00","6":"Online","location":"Online","7":"aldkfj;ladsjf","description":"aldkfj;ladsjf","8":"1Riddler81722.jpg","poster":"1Riddler81722.jpg","9":"1Riddler2090.jpg","permission":"1Riddler2090.jpg","10":"yes","verificationStatus":"yes"}]